sat_automations/__init__.py
sat_automations/conftest.py
sat_automations/demo_automation/__init__.py
sat_automations/demo_automation/admin.py
sat_automations/demo_automation/apps.py
sat_automations/demo_automation/models.py
sat_automations/demo_automation/tasks.py
sat_automations/demo_automation/urls.py
sat_automations/demo_automation/views.py
sat_automations/demo_automation/migrations/__init__.py
sat_automations/demo_automation/tests/__init__.py
sat_automations/demo_automation/tests/test_tasks.py
sat_automations/disablement_automation/__init__.py
sat_automations/disablement_automation/admin.py
sat_automations/disablement_automation/apps.py
sat_automations/disablement_automation/config.py
sat_automations/disablement_automation/models.py
sat_automations/disablement_automation/tasks.py
sat_automations/disablement_automation/urls.py
sat_automations/disablement_automation/views.py
sat_automations/disablement_automation/migrations/0001_initial.py
sat_automations/disablement_automation/migrations/__init__.py
sat_automations/disablement_automation/tests/__init__.py
sat_automations/disablement_automation/tests/test_admin.py
sat_automations/disablement_automation/tests/test_models.py
sat_automations/gold_feed_automation/__init__.py
sat_automations/gold_feed_automation/admin.py
sat_automations/gold_feed_automation/apps.py
sat_automations/gold_feed_automation/config.py
sat_automations/gold_feed_automation/helper_queries.py
sat_automations/gold_feed_automation/models.py
sat_automations/gold_feed_automation/tasks.py
sat_automations/gold_feed_automation/urls.py
sat_automations/gold_feed_automation/views.py
sat_automations/gold_feed_automation/migrations/__init__.py
sat_automations/gold_feed_automation/tests/__init__.py
sat_automations/gold_feed_automation/tests/fixtures.py
sat_automations/gold_feed_automation/tests/test_tasks.py
sat_automations/housing_automation/__init__.py
sat_automations/housing_automation/admin.py
sat_automations/housing_automation/apps.py
sat_automations-0.5.17rc11.dist-info/LICENSE
sat_automations-0.5.17rc11.dist-info/WHEEL
sat_automations-0.5.17rc11.dist-info/METADATA
sat_automations-0.5.17rc11.dist-info/RECORD
