Metadata-Version: 2.1
Name: sat-automations
Version: 0.5.17rc11
Summary: Contains a collection celery based apps
Author-email: Jeremy Gibson <jmgibso3@ncsu.edu>, John Champion <jtchampi@ncsu.edu>, Ravi Teja Jujjuri <rtjujjur@ncsu.edu>
Requires-Python: >=3.9
Requires-Dist: django>=4.2.0, <5.0.0
Requires-Dist: celery[redis]>=5.2.7, <6.0.0
Requires-Dist: django-celery-results>=2.5.1, <3.0.0
Requires-Dist: django-celery-beat>=2.5.0, <3.0.0
Requires-Dist: django-model-utils>=4.3.1, <5.0.0
Requires-Dist: sat-utils>=1.1.12, <2.0.0
Requires-Dist: pymongo>=3.13.0, <4.3.3
Requires-Dist: django-simple-history>=3.3.0, <4.0.0
Requires-Dist: google-auth>=2.19.1, <3.0.0
Requires-Dist: pytest>=6.2.5, <7.0.0 ; extra == "dev"
Requires-Dist: pytest-django>=4.5.2, <5.0.0 ; extra == "dev"
Requires-Dist: pytest-mock>=3.10.0, <4.0.0 ; extra == "dev"
Requires-Dist: pytest-cov>=4.0.0, <5.0.0 ; extra == "dev"
Requires-Dist: Faker>=18.11.2, <19.0.0 ; extra == "dev"
Requires-Dist: coverage[toml]>=6.2 ; extra == "dev"
Requires-Dist: pytest-celery>=0.0.0, <1.0.0 ; extra == "dev"
Requires-Dist: black>=23.3.0, <24.0.0 ; extra == "dev"
Requires-Dist: mypy>=1.2.0, <2.0.0 ; extra == "dev"
Requires-Dist: ruff==0.0.263 ; extra == "dev"
Requires-Dist: mkdocs-material>=9.1.6, <10.0.0 ; extra == "dev"
Requires-Dist: Pygments>=2.10.0, <3.0.0 ; extra == "dev"
Requires-Dist: bandit>=1.7.4, <2.0.0 ; extra == "dev"
Requires-Dist: pre-commit>=2.16.0, <3.0.0 ; extra == "dev"
Requires-Dist: isort>=5.10.1, <6.0.0 ; extra == "dev"
Requires-Dist: pyupgrade>=2.29.1, <3.0.0 ; extra == "dev"
Requires-Dist: ipython>=8.13.0, <9.0.0 ; extra == "dev"
Requires-Dist: flit>=3.8.0, <4.0.0 ; extra == "dev"
Requires-Dist: beautifulsoup4>=4.12.2, <5.0.0 ; extra == "dev"
Project-URL: Homepage, https://github.ncsu.edu/SAT/sat-automations
Provides-Extra: dev
